sumeru/__init__.py
sumeru/_concurrent_futures_thread.py
sumeru/_ipython_utils.py
sumeru/_version.py
sumeru/actor.py
sumeru/asyncio.py
sumeru/batched.py
sumeru/cfexecutor.py
sumeru/client.py
sumeru/compatibility.py
sumeru/config.py
sumeru/core.py
sumeru/counter.py
sumeru/diskutils.py
sumeru/joblib.py
sumeru/lock.py
sumeru/locket.py
sumeru/logo.py
sumeru/metrics.py
sumeru/nanny.py
sumeru/node.py
sumeru/preloading.py
sumeru/process.py
sumeru/proctitle.py
sumeru/profile.py
sumeru/publish.py
sumeru/pubsub.py
sumeru/pytest_resourceleaks.py
sumeru/queues.py
sumeru/recreate_exceptions.py
sumeru/scheduler.py
sumeru/security.py
sumeru/sizeof.py
sumeru/stealing.py
sumeru/submit.py
sumeru/sumeru.yaml
sumeru/system_monitor.py
sumeru/threadpoolexecutor.py
sumeru/utils.py
sumeru/utils_comm.py
sumeru/utils_perf.py
sumeru/utils_test.py
sumeru/variable.py
sumeru/versions.py
sumeru/worker.py
sumeru/worker_client.py
sumeru/bokeh/__init__.py
sumeru/bokeh/components.py
sumeru/bokeh/core.py
sumeru/bokeh/export_tool.coffee
sumeru/bokeh/export_tool.js
sumeru/bokeh/export_tool.py
sumeru/bokeh/scheduler.py
sumeru/bokeh/scheduler_html.py
sumeru/bokeh/theme.yaml
sumeru/bokeh/utils.py
sumeru/bokeh/worker.py
sumeru/bokeh/static/css/base.css
sumeru/bokeh/static/css/status.css
sumeru/bokeh/static/images/dask-logo.svg
sumeru/bokeh/static/images/fa-bars.svg
sumeru/bokeh/templates/base.html
sumeru/bokeh/templates/call-stack.html
sumeru/bokeh/templates/json-index.html
sumeru/bokeh/templates/logs.html
sumeru/bokeh/templates/main.html
sumeru/bokeh/templates/simple.html
sumeru/bokeh/templates/status.html
sumeru/bokeh/templates/task.html
sumeru/bokeh/templates/worker-table.html
sumeru/bokeh/templates/worker.html
sumeru/bokeh/templates/workers.html
sumeru/bokeh/tests/test_components.py
sumeru/bokeh/tests/test_scheduler_bokeh.py
sumeru/bokeh/tests/test_scheduler_bokeh_html.py
sumeru/bokeh/tests/test_worker_bokeh.py
sumeru/cli/__init__.py
sumeru/cli/sumeru_mpi.py
sumeru/cli/sumeru_remote.py
sumeru-0.10.3.dist-info/METADATA
sumeru-0.10.3.dist-info/WHEEL
sumeru-0.10.3.dist-info/entry_points.txt
sumeru-0.10.3.dist-info/top_level.txt
sumeru-0.10.3.dist-info/RECORD
