Metadata-Version: 2.1
Name: sumeru
Version: 0.10.3
Summary: Sumeru
Home-page: UNKNOWN
Maintainer: sumeru
License: BSD
Platform: UNKNOWN
Classifier: Development Status :: 5 - Production/Stable
Classifier: Intended Audience :: Developers
Classifier: Intended Audience :: Science/Research
Classifier: License :: OSI Approved :: BSD License
Classifier: Operating System :: OS Independent
Classifier: Programming Language :: Python
Classifier: Programming Language :: Python :: 2.7
Classifier: Programming Language :: Python :: 3.5
Classifier: Programming Language :: Python :: 3.6
Classifier: Programming Language :: Python :: 3.7
Classifier: Topic :: Scientific/Engineering
Classifier: Topic :: System :: Distributed Computing
Requires-Dist: click (>=6.6)
Requires-Dist: cloudpickle (>=0.2.2)
Requires-Dist: msgpack
Requires-Dist: psutil
Requires-Dist: six
Requires-Dist: sortedcontainers (!=2.0.0,!=2.0.1)
Requires-Dist: tblib
Requires-Dist: toolz (>=0.7.4)
Requires-Dist: zict (>=0.1.3)
Requires-Dist: futures (==3.1.1)
Requires-Dist: singledispatch
Requires-Dist: pyyaml
Requires-Dist: dill (==0.2.6)
Requires-Dist: peewee (==3.6.4)
Requires-Dist: tornado (==5.1.0)
Requires-Dist: redis (==2.10.5)
Requires-Dist: gevent
Requires-Dist: redislite
Requires-Dist: pymysql
Requires-Dist: python-etcd
Requires-Dist: aio-etcd
